{
  "url": "https://www.tiktok.com/@dtran55/video/7255558002583981317",
  "crawled_at": "2025-11-07T16:14:25.317384Z",
  "oembed": {
    "version": "1.0",
    "type": "video",
    "title": "Túi thần chửi =)#fyp #capcut #fypシ #fypシ゚viral #xuhuong #xuhuongtiktok #trending #trend #xuhuongtiktok2023 #xuhuong2023 #vba2023 #funnyvideos #funnyvideo #meme #foryou #funny ",
    "author_url": "https://www.tiktok.com/@dtran55",
    "author_name": "Dương?",
    "width": "100%",
    "height": "100%",
    "html": "<blockquote class=\"tiktok-embed\" cite=\"https://www.tiktok.com/@dtran55/video/7255558002583981317\" data-video-id=\"7255558002583981317\" data-embed-from=\"oembed\" style=\"max-width:605px; min-width:325px;\"> <section> <a target=\"_blank\" title=\"@dtran55\" href=\"https://www.tiktok.com/@dtran55?refer=embed\">@dtran55</a> <p>Túi thần chửi =)<a title=\"fyp\" target=\"_blank\" href=\"https://www.tiktok.com/tag/fyp?refer=embed\">#fyp</a> <a title=\"capcut\" target=\"_blank\" href=\"https://www.tiktok.com/tag/capcut?refer=embed\">#capcut</a> <a title=\"fypシ\" target=\"_blank\" href=\"https://www.tiktok.com/tag/fyp%E3%82%B7?refer=embed\">#fypシ</a> <a title=\"fypシ゚viral\" target=\"_blank\" href=\"https://www.tiktok.com/tag/fyp%E3%82%B7%E3%82%9Aviral?refer=embed\">#fypシ゚viral</a> <a title=\"xuhuong\" target=\"_blank\" href=\"https://www.tiktok.com/tag/xuhuong?refer=embed\">#xuhuong</a> <a title=\"xuhuongtiktok\" target=\"_blank\" href=\"https://www.tiktok.com/tag/xuhuongtiktok?refer=embed\">#xuhuongtiktok</a> <a title=\"trending\" target=\"_blank\" href=\"https://www.tiktok.com/tag/trending?refer=embed\">#trending</a> <a title=\"trend\" target=\"_blank\" href=\"https://www.tiktok.com/tag/trend?refer=embed\">#trend</a> <a title=\"xuhuongtiktok2023\" target=\"_blank\" href=\"https://www.tiktok.com/tag/xuhuongtiktok2023?refer=embed\">#xuhuongtiktok2023</a> <a title=\"xuhuong2023\" target=\"_blank\" href=\"https://www.tiktok.com/tag/xuhuong2023?refer=embed\">#xuhuong2023</a> <a title=\"vba2023\" target=\"_blank\" href=\"https://www.tiktok.com/tag/vba2023?refer=embed\">#vba2023</a> <a title=\"funnyvideos\" target=\"_blank\" href=\"https://www.tiktok.com/tag/funnyvideos?refer=embed\">#funnyvideos</a> <a title=\"funnyvideo\" target=\"_blank\" href=\"https://www.tiktok.com/tag/funnyvideo?refer=embed\">#funnyvideo</a> <a title=\"meme\" target=\"_blank\" href=\"https://www.tiktok.com/tag/meme?refer=embed\">#meme</a> <a title=\"foryou\" target=\"_blank\" href=\"https://www.tiktok.com/tag/foryou?refer=embed\">#foryou</a> <a title=\"funny\" target=\"_blank\" href=\"https://www.tiktok.com/tag/funny?refer=embed\">#funny</a> </p> <a target=\"_blank\" title=\"♬ nhạc nền - Chào t làm chó - Dương?\" href=\"https://www.tiktok.com/music/nhạc-nền-Chào-t-làm-chó-7255557993826896645?refer=embed\">♬ nhạc nền - Chào t làm chó - Dương?</a> </section> </blockquote> <script async src=\"https://www.tiktok.com/embed.js\"></script>",
    "thumbnail_width": 1080,
    "thumbnail_height": 1920,
    "thumbnail_url": "https://p16-sign-va.tiktokcdn.com/tos-maliva-p-0068/oceDQ6s5I5VEJOsBgwMnbBmRtZAeCjOQYbGkQx~tplv-tiktokx-origin.image?dr=14575&x-expires=1762704000&x-signature=sc1wlEdVQwjSVBtR7tK4V18IboI%3D&t=4d5b0474&ps=13740610&shp=81f88b70&shcp=43f4a2f9&idc=my2",
    "provider_url": "https://www.tiktok.com",
    "provider_name": "TikTok",
    "author_unique_id": "dtran55",
    "embed_product_id": "7255558002583981317",
    "embed_type": "video"
  },
  "yt_dlp_info": {
    "id": "7255558002583981317",
    "formats": [
      {
        "ext": "mp4",
        "vcodec": "h264",
        "acodec": "aac",
        "format_id": "download",
        "url": "https://v16-webapp-prime.tiktok.com/video/tos/maliva/tos-maliva-ve-0068c801-us/oAjQ1Od5noNzmhVtAsegJURZgBbfkDBQDHQxEs/?a=1988&bti=ODszNWYuMDE6&ch=0&cr=3&dr=0&lr=all&cd=0%7C0%7C0%7C&br=4052&bt=2026&cs=0&ds=3&ft=-Csk_mH1PD12NfOFHd-UxZGFaY6e3wv25IcAp&mime_type=video_mp4&qs=0&rc=cnF8b2hsc2d3SkBwaHIxaDFybndmNDZmNGg6M2g2NWU0NzhnZUBpamo0aGQ6ZnBobDMzNzczM0BjRl5Nc3FePmJKYSNvYF90aHFmOiMzLzUwMC8uNl4xM142LjUyYSM2YDJycjRfamxgLS1kMTZzcw%3D%3D&btag=e000b0000&expire=1762704873&l=202511080014255444463DE6AB2CDA0117&ply_type=2&policy=2&signature=1635084f6281a62b422bec05cc205c18&tk=tt_chain_token",
        "format_note": "watermarked",
        "preference": -2,
        "protocol": "https",
        "video_ext": "mp4",
        "audio_ext": "none",
        "dynamic_range": "SDR",
        "cookies": "_ttp=34wyWDXvxmF602Htsl0oDR6JCNq; Domain=.tiktok.com; Path=/; Secure; Expires=1795834961; tt_csrf_token=A6kVUZcK-ro_L6C62WbmQwfALArHC4HF-pTM; Domain=.tiktok.com; Path=/; Secure; tt_chain_token=\"bIQCOyoJbQ000pox+IBxHQ==\"; Domain=.tiktok.com; Path=/; Secure; Expires=1778084066; passport_csrf_token=3e2175a5e77e24a26515b4e6f7b50740; Domain=.tiktok.com; Path=/; Secure; Expires=1767674732; passport_csrf_token_default=3e2175a5e77e24a26515b4e6f7b50740; Domain=.tiktok.com; Path=/; Secure; Expires=1767674732; s_v_web_id=verify_mhodh7s9_f6H7RhcI_zN3b_4VwP_AxSW_OnDGZUzFJBgu; Domain=.tiktok.com; Path=/; Secure; multi_sids=7569810985282094098%3Aade59ff71c0c0e5cc0fe1f23772b37c1; Domain=.tiktok.com; Path=/; Secure; Expires=1767677004; cmpl_token=AgQQAPOFF-RO0rkzsFuCpB0r82zGAoWNv4UOYKOhVw; Domain=.tiktok.com; Path=/; Secure; Expires=1767677004; passport_auth_status=b8d801922a4b455b405bf6994fade073%2C063941b21aed31105bffa0d912bcf9fa; Domain=.tiktok.com; Path=/; Expires=1765085004; passport_auth_status_ss=b8d801922a4b455b405bf6994fade073%2C063941b21aed31105bffa0d912bcf9fa; Domain=.tiktok.com; Path=/; Secure; Expires=1765085004; sid_guard=ade59ff71c0c0e5cc0fe1f23772b37c1%7C1762493004%7C15552000%7CWed%2C+06-May-2026+05%3A23%3A24+GMT; Domain=.tiktok.com; Path=/; Secure; Expires=1793597004; uid_tt=ac0557b89a0248004ba199e09ced5e656aa70515a78deb5b62cd048a83d31edc; Domain=.tiktok.com; Path=/; Secure; Expires=1778045004; uid_tt_ss=ac0557b89a0248004ba199e09ced5e656aa70515a78deb5b62cd048a83d31edc; Domain=.tiktok.com; Path=/; Secure; Expires=1778045004; sid_tt=ade59ff71c0c0e5cc0fe1f23772b37c1; Domain=.tiktok.com; Path=/; Secure; Expires=1778045004; sessionid=ade59ff71c0c0e5cc0fe1f23772b37c1; Domain=.tiktok.com; Path=/; Secure; Expires=1778045004; sessionid_ss=ade59ff71c0c0e5cc0fe1f23772b37c1; Domain=.tiktok.com; Path=/; Secure; Expires=1778045004; tt_session_tlb_tag=sttt%7C5%7CreWf9xwMDlzA_h8jdys3wf________-ji4fpfjT0V1140MZnLSHWNBnXgRLIZvw1fxmxRRmvw7s%3D; Domain=.tiktok.com; Path=/; Secure; Expires=1778045004; sid_ucp_v1=1.0.0-KDYzMTBmY2U1ODFjN2FkYjNmOGUwYWE1YjcwYTk2N2FkYzhhMjMxMTEKIQiSiNvUwN_XhmkQzIS2yAYYswsgDDC1vrXIBjgIQBJIBBADGgJteSIgYWRlNTlmZjcxYzBjMGU1Y2MwZmUxZjIzNzcyYjM3YzE; Domain=.tiktok.com; Path=/; Secure; Expires=1778045004; ssid_ucp_v1=1.0.0-KDYzMTBmY2U1ODFjN2FkYjNmOGUwYWE1YjcwYTk2N2FkYzhhMjMxMTEKIQiSiNvUwN_XhmkQzIS2yAYYswsgDDC1vrXIBjgIQBJIBBADGgJteSIgYWRlNTlmZjcxYzBjMGU1Y2MwZmUxZjIzNzcyYjM3YzE; Domain=.tiktok.com; Path=/; Secure; Expires=1778045004; store-country-code=vn; Domain=.tiktok.com; Path=/; Expires=1794029034; store-country-code-src=uid; Domain=.tiktok.com; Path=/; Expires=1794029034; tt-target-idc=alisg; Domain=.tiktok.com; Path=/; Expires=1794029034; tt-target-idc-sign=X46gRkvSgmGWHXja-gzeN1KwdE4cBtH3zFXAhG3-BtWzH-YdFZEQct_uBwMTYtfjrNxqy_GJyyU9vrDSU9xBVMhZYzNMj8Yj-vL3ZdUiBlJfwT_RyqsMw9cBp-UMAurlaLw7iKPn1sOB_2Mr4OgfdC72r1rSon8aLN6RpZxfHlcPgzQDAzxGLO1WCcDi3Grn071JYzpIP3H4Uj5tKf5cHSGRn8O-z3hwE-QaTWdxP_Dv9m7mqKXg9LpTBaiRQ0apSWQMga4QK4y5B4To6e0pZD8oaixa2PVdqGeLesDSGOjsT94m5Qtsw2dBLvi1Cl2PDtg34s_m8F2kwZanwVGyMx5JeHbhEA1jVyuFTZ4wmF-6mQMCj4IoVYUBqf6cEHJl1nz6p3h7j4AFPdhgbDj7nwn0zI1o0xP8WGmE_kn9e53ehBx6IU-iOQJ-JXc_4e8_1n_tP7nZqBQAfB5B-a8mW0iUyH2XBzKKIebPZ8u02eRKDVUUZnutFcgBXjbQW4hW; Domain=.tiktok.com; Path=/; Expires=1794029034; ttwid=1%7CyHVVoWeMmc-3HMQzGeLAWTKsoEmn5lOxHLhrceV4g3w%7C1762493033%7Caa33d6157603beb187ae2fd554015cf463e69a9385fbc54d7a3e7a848a9df8fc; Domain=.tiktok.com; Path=/; Secure; Expires=1794029034; store-idc=alisg; Domain=.tiktok.com; Path=/; Expires=1794029034; store-country-sign=MEIEDGNAqWqR2a0er4zjeAQgMuurAVNuf3SOpc_lCsUS6OVOTEMJPGY7fje3VCShvuYEEKSUWUChT9xgz3oinfsoj_8; Domain=.tiktok.com; Path=/; Expires=1794029034; odin_tt=fdb338ea9924b66e069cd3826b52e91602d6c7c70440ed4a45253d1bdcb67e7b33079c363923c1afe01be7d6a0aed5f094b6d26ad61219129e2c4adf8ef71b17c80e515b61a158847d9b8a0bdf5ce20d; Domain=.tiktok.com; Path=/; Expires=1794029677; msToken=\"kAcg9UuK5ZrneVDkYKsMPRcYLs1WAe9Bb0dpY3v2-xiyVx5Y6WfL8b6hWSn8iwVU3aEtG7I1jp1bvznmNsWneQmhuN9QHhnLK0KGHJ3hFP03j-bKzuS-NgPmvvyp3T7C_urkuuRQ27R5xw==\"; Domain=.tiktok.com; Path=/; Secure; Expires=1763396065",
        "http_headers": {
          "User-Agent": "Mozilla/5.0",
          "Accept": "text/html,application/xhtml+xml,application/xml;q=0.9,*/*;q=0.8",
          "Accept-Language": "en-us,en;q=0.5",
          "Sec-Fetch-Mode": "navigate",
          "Referer": "https://www.tiktok.com/@dtran55/video/7255558002583981317"
        },
        "format": "download - unknown (watermarked)"
      },
      {
        "ext": "mp4",
        "vcodec": "h264",
        "acodec": "aac",
        "format_id": "play",
        "url": "https://v16-webapp-prime.tiktok.com/video/tos/alisg/tos-alisg-v-37c810-sg/oQE8kIAyPWw6WfWBKTCz1oACkQgtAs8AoEA4hH/?a=1988&bti=ODszNWYuMDE6&ch=0&cr=3&dr=0&lr=all&cd=0%7C0%7C0%7C&br=24910&bt=12455&ds=4&ft=-Csk_mH1PD12NfOFHd-UxZGFaY6e3wv25IcAp&mime_type=video_mp4&qs=13&rc=cnF8b2hsc2d3SkBwaHIxaDFybndmamo0aGQ6ZnBobDMzNzczM0Bpamo0aGQ6ZnBobDMzNzczM0BjRl5Nc3FePmJKYSNvYF90aHFmOiM2YDJycjRfamxgLS1kMTZzYSM2YDJycjRfamxgLS1kMTZzcw%3D%3D&btag=e00070000&expire=1762704873&l=202511080014255444463DE6AB2CDA0117&ply_type=2&policy=2&signature=1ade88d1f6ec11404b23867af53bab07&tk=tt_chain_token",
        "width": 1080,
        "height": 1920,
        "protocol": "https",
        "video_ext": "mp4",
        "audio_ext": "none",
        "resolution": "1080x1920",
        "dynamic_range": "SDR",
        "aspect_ratio": 0.56,
        "cookies": "_ttp=34wyWDXvxmF602Htsl0oDR6JCNq; Domain=.tiktok.com; Path=/; Secure; Expires=1795834961; tt_csrf_token=A6kVUZcK-ro_L6C62WbmQwfALArHC4HF-pTM; Domain=.tiktok.com; Path=/; Secure; tt_chain_token=\"bIQCOyoJbQ000pox+IBxHQ==\"; Domain=.tiktok.com; Path=/; Secure; Expires=1778084066; passport_csrf_token=3e2175a5e77e24a26515b4e6f7b50740; Domain=.tiktok.com; Path=/; Secure; Expires=1767674732; passport_csrf_token_default=3e2175a5e77e24a26515b4e6f7b50740; Domain=.tiktok.com; Path=/; Secure; Expires=1767674732; s_v_web_id=verify_mhodh7s9_f6H7RhcI_zN3b_4VwP_AxSW_OnDGZUzFJBgu; Domain=.tiktok.com; Path=/; Secure; multi_sids=7569810985282094098%3Aade59ff71c0c0e5cc0fe1f23772b37c1; Domain=.tiktok.com; Path=/; Secure; Expires=1767677004; cmpl_token=AgQQAPOFF-RO0rkzsFuCpB0r82zGAoWNv4UOYKOhVw; Domain=.tiktok.com; Path=/; Secure; Expires=1767677004; passport_auth_status=b8d801922a4b455b405bf6994fade073%2C063941b21aed31105bffa0d912bcf9fa; Domain=.tiktok.com; Path=/; Expires=1765085004; passport_auth_status_ss=b8d801922a4b455b405bf6994fade073%2C063941b21aed31105bffa0d912bcf9fa; Domain=.tiktok.com; Path=/; Secure; Expires=1765085004; sid_guard=ade59ff71c0c0e5cc0fe1f23772b37c1%7C1762493004%7C15552000%7CWed%2C+06-May-2026+05%3A23%3A24+GMT; Domain=.tiktok.com; Path=/; Secure; Expires=1793597004; uid_tt=ac0557b89a0248004ba199e09ced5e656aa70515a78deb5b62cd048a83d31edc; Domain=.tiktok.com; Path=/; Secure; Expires=1778045004; uid_tt_ss=ac0557b89a0248004ba199e09ced5e656aa70515a78deb5b62cd048a83d31edc; Domain=.tiktok.com; Path=/; Secure; Expires=1778045004; sid_tt=ade59ff71c0c0e5cc0fe1f23772b37c1; Domain=.tiktok.com; Path=/; Secure; Expires=1778045004; sessionid=ade59ff71c0c0e5cc0fe1f23772b37c1; Domain=.tiktok.com; Path=/; Secure; Expires=1778045004; sessionid_ss=ade59ff71c0c0e5cc0fe1f23772b37c1; Domain=.tiktok.com; Path=/; Secure; Expires=1778045004; tt_session_tlb_tag=sttt%7C5%7CreWf9xwMDlzA_h8jdys3wf________-ji4fpfjT0V1140MZnLSHWNBnXgRLIZvw1fxmxRRmvw7s%3D; Domain=.tiktok.com; Path=/; Secure; Expires=1778045004; sid_ucp_v1=1.0.0-KDYzMTBmY2U1ODFjN2FkYjNmOGUwYWE1YjcwYTk2N2FkYzhhMjMxMTEKIQiSiNvUwN_XhmkQzIS2yAYYswsgDDC1vrXIBjgIQBJIBBADGgJteSIgYWRlNTlmZjcxYzBjMGU1Y2MwZmUxZjIzNzcyYjM3YzE; Domain=.tiktok.com; Path=/; Secure; Expires=1778045004; ssid_ucp_v1=1.0.0-KDYzMTBmY2U1ODFjN2FkYjNmOGUwYWE1YjcwYTk2N2FkYzhhMjMxMTEKIQiSiNvUwN_XhmkQzIS2yAYYswsgDDC1vrXIBjgIQBJIBBADGgJteSIgYWRlNTlmZjcxYzBjMGU1Y2MwZmUxZjIzNzcyYjM3YzE; Domain=.tiktok.com; Path=/; Secure; Expires=1778045004; store-country-code=vn; Domain=.tiktok.com; Path=/; Expires=1794029034; store-country-code-src=uid; Domain=.tiktok.com; Path=/; Expires=1794029034; tt-target-idc=alisg; Domain=.tiktok.com; Path=/; Expires=1794029034; tt-target-idc-sign=X46gRkvSgmGWHXja-gzeN1KwdE4cBtH3zFXAhG3-BtWzH-YdFZEQct_uBwMTYtfjrNxqy_GJyyU9vrDSU9xBVMhZYzNMj8Yj-vL3ZdUiBlJfwT_RyqsMw9cBp-UMAurlaLw7iKPn1sOB_2Mr4OgfdC72r1rSon8aLN6RpZxfHlcPgzQDAzxGLO1WCcDi3Grn071JYzpIP3H4Uj5tKf5cHSGRn8O-z3hwE-QaTWdxP_Dv9m7mqKXg9LpTBaiRQ0apSWQMga4QK4y5B4To6e0pZD8oaixa2PVdqGeLesDSGOjsT94m5Qtsw2dBLvi1Cl2PDtg34s_m8F2kwZanwVGyMx5JeHbhEA1jVyuFTZ4wmF-6mQMCj4IoVYUBqf6cEHJl1nz6p3h7j4AFPdhgbDj7nwn0zI1o0xP8WGmE_kn9e53ehBx6IU-iOQJ-JXc_4e8_1n_tP7nZqBQAfB5B-a8mW0iUyH2XBzKKIebPZ8u02eRKDVUUZnutFcgBXjbQW4hW; Domain=.tiktok.com; Path=/; Expires=1794029034; ttwid=1%7CyHVVoWeMmc-3HMQzGeLAWTKsoEmn5lOxHLhrceV4g3w%7C1762493033%7Caa33d6157603beb187ae2fd554015cf463e69a9385fbc54d7a3e7a848a9df8fc; Domain=.tiktok.com; Path=/; Secure; Expires=1794029034; store-idc=alisg; Domain=.tiktok.com; Path=/; Expires=1794029034; store-country-sign=MEIEDGNAqWqR2a0er4zjeAQgMuurAVNuf3SOpc_lCsUS6OVOTEMJPGY7fje3VCShvuYEEKSUWUChT9xgz3oinfsoj_8; Domain=.tiktok.com; Path=/; Expires=1794029034; odin_tt=fdb338ea9924b66e069cd3826b52e91602d6c7c70440ed4a45253d1bdcb67e7b33079c363923c1afe01be7d6a0aed5f094b6d26ad61219129e2c4adf8ef71b17c80e515b61a158847d9b8a0bdf5ce20d; Domain=.tiktok.com; Path=/; Expires=1794029677; msToken=\"kAcg9UuK5ZrneVDkYKsMPRcYLs1WAe9Bb0dpY3v2-xiyVx5Y6WfL8b6hWSn8iwVU3aEtG7I1jp1bvznmNsWneQmhuN9QHhnLK0KGHJ3hFP03j-bKzuS-NgPmvvyp3T7C_urkuuRQ27R5xw==\"; Domain=.tiktok.com; Path=/; Secure; Expires=1763396065",
        "http_headers": {
          "User-Agent": "Mozilla/5.0",
          "Accept": "text/html,application/xhtml+xml,application/xml;q=0.9,*/*;q=0.8",
          "Accept-Language": "en-us,en;q=0.5",
          "Sec-Fetch-Mode": "navigate",
          "Referer": "https://www.tiktok.com/@dtran55/video/7255558002583981317"
        },
        "format": "play - 1080x1920"
      }
    ],
    "subtitles": {},
    "http_headers": {
      "User-Agent": "Mozilla/5.0",
      "Accept": "text/html,application/xhtml+xml,application/xml;q=0.9,*/*;q=0.8",
      "Accept-Language": "en-us,en;q=0.5",
      "Sec-Fetch-Mode": "navigate",
      "Referer": "https://www.tiktok.com/@dtran55/video/7255558002583981317"
    },
    "channel": "Dương?",
    "channel_id": "MS4wLjABAAAAQvDFLHkdj7i4mFsrFRmN39ob6nXlxHamoAgwWOuDjJNvv8JeTaZkqn1GM2W5AcDk",
    "uploader": "dtran55",
    "uploader_id": "7214062514865374210",
    "channel_url": "https://www.tiktok.com/@MS4wLjABAAAAQvDFLHkdj7i4mFsrFRmN39ob6nXlxHamoAgwWOuDjJNvv8JeTaZkqn1GM2W5AcDk",
    "uploader_url": "https://www.tiktok.com/@dtran55",
    "track": "nhạc nền - Chào t làm chó",
    "artists": [
      "Dương?"
    ],
    "duration": 7,
    "title": "Túi thần chửi =)#fyp #capcut #fypシ #fypシ゚viral #xuhuong #xuhuongtikto...",
    "description": "Túi thần chửi =)#fyp #capcut #fypシ #fypシ゚viral #xuhuong #xuhuongtiktok #trending #trend #xuhuongtiktok2023 #xuhuong2023 #vba2023 #funnyvideos #funnyvideo #meme #foryou #funny ",
    "timestamp": 1689316244,
    "view_count": 52200,
    "like_count": 458,
    "repost_count": 736,
    "comment_count": 9,
    "thumbnails": [
      {
        "id": "dynamicCover",
        "url": "https://p16-sign-va.tiktokcdn.com/tos-maliva-p-0068/ce7ac5d0dcca4071b6c75996843a81ae_1689316248~tplv-tiktokx-origin.image?dr=14575&x-expires=1762704000&x-signature=g%2Buxp%2BEg6uIcrqXM0EhRJpFG02U%3D&t=4d5b0474&ps=13740610&shp=81f88b70&shcp=43f4a2f9&idc=my2",
        "preference": -2
      },
      {
        "id": "cover",
        "url": "https://p16-sign-va.tiktokcdn.com/tos-maliva-p-0068/oceDQ6s5I5VEJOsBgwMnbBmRtZAeCjOQYbGkQx~tplv-tiktokx-origin.image?dr=14575&x-expires=1762704000&x-signature=sc1wlEdVQwjSVBtR7tK4V18IboI%3D&t=4d5b0474&ps=13740610&shp=81f88b70&shcp=43f4a2f9&idc=my2",
        "preference": -1
      },
      {
        "id": "originCover",
        "url": "https://p16-sign-va.tiktokcdn.com/tos-maliva-p-0068/8a5fcdc040784d6c9ddb0e8bfde26dfb_1689316248~tplv-tiktokx-origin.image?dr=14575&x-expires=1762704000&x-signature=W23i1LkLrZWSBV8gYCOK%2BOH6qUs%3D&t=4d5b0474&ps=13740610&shp=81f88b70&shcp=43f4a2f9&idc=my2",
        "preference": -1
      }
    ],
    "webpage_url": "https://www.tiktok.com/@dtran55/video/7255558002583981317",
    "webpage_url_basename": "7255558002583981317",
    "webpage_url_domain": "tiktok.com",
    "extractor": "TikTok",
    "extractor_key": "TikTok",
    "thumbnail": "https://p16-sign-va.tiktokcdn.com/tos-maliva-p-0068/8a5fcdc040784d6c9ddb0e8bfde26dfb_1689316248~tplv-tiktokx-origin.image?dr=14575&x-expires=1762704000&x-signature=W23i1LkLrZWSBV8gYCOK%2BOH6qUs%3D&t=4d5b0474&ps=13740610&shp=81f88b70&shcp=43f4a2f9&idc=my2",
    "display_id": "7255558002583981317",
    "fulltitle": "Túi thần chửi =)#fyp #capcut #fypシ #fypシ゚viral #xuhuong #xuhuongtikto...",
    "duration_string": "7",
    "upload_date": "20230714",
    "artist": "Dương?",
    "epoch": 1762532066,
    "ext": "mp4",
    "vcodec": "h264",
    "acodec": "aac",
    "format_id": "play",
    "url": "https://v16-webapp-prime.tiktok.com/video/tos/alisg/tos-alisg-v-37c810-sg/oQE8kIAyPWw6WfWBKTCz1oACkQgtAs8AoEA4hH/?a=1988&bti=ODszNWYuMDE6&ch=0&cr=3&dr=0&lr=all&cd=0%7C0%7C0%7C&br=24910&bt=12455&ds=4&ft=-Csk_mH1PD12NfOFHd-UxZGFaY6e3wv25IcAp&mime_type=video_mp4&qs=13&rc=cnF8b2hsc2d3SkBwaHIxaDFybndmamo0aGQ6ZnBobDMzNzczM0Bpamo0aGQ6ZnBobDMzNzczM0BjRl5Nc3FePmJKYSNvYF90aHFmOiM2YDJycjRfamxgLS1kMTZzYSM2YDJycjRfamxgLS1kMTZzcw%3D%3D&btag=e00070000&expire=1762704873&l=202511080014255444463DE6AB2CDA0117&ply_type=2&policy=2&signature=1ade88d1f6ec11404b23867af53bab07&tk=tt_chain_token",
    "width": 1080,
    "height": 1920,
    "protocol": "https",
    "video_ext": "mp4",
    "audio_ext": "none",
    "resolution": "1080x1920",
    "dynamic_range": "SDR",
    "aspect_ratio": 0.56,
    "cookies": "_ttp=34wyWDXvxmF602Htsl0oDR6JCNq; Domain=.tiktok.com; Path=/; Secure; Expires=1795834961; tt_csrf_token=A6kVUZcK-ro_L6C62WbmQwfALArHC4HF-pTM; Domain=.tiktok.com; Path=/; Secure; tt_chain_token=\"bIQCOyoJbQ000pox+IBxHQ==\"; Domain=.tiktok.com; Path=/; Secure; Expires=1778084066; passport_csrf_token=3e2175a5e77e24a26515b4e6f7b50740; Domain=.tiktok.com; Path=/; Secure; Expires=1767674732; passport_csrf_token_default=3e2175a5e77e24a26515b4e6f7b50740; Domain=.tiktok.com; Path=/; Secure; Expires=1767674732; s_v_web_id=verify_mhodh7s9_f6H7RhcI_zN3b_4VwP_AxSW_OnDGZUzFJBgu; Domain=.tiktok.com; Path=/; Secure; multi_sids=7569810985282094098%3Aade59ff71c0c0e5cc0fe1f23772b37c1; Domain=.tiktok.com; Path=/; Secure; Expires=1767677004; cmpl_token=AgQQAPOFF-RO0rkzsFuCpB0r82zGAoWNv4UOYKOhVw; Domain=.tiktok.com; Path=/; Secure; Expires=1767677004; passport_auth_status=b8d801922a4b455b405bf6994fade073%2C063941b21aed31105bffa0d912bcf9fa; Domain=.tiktok.com; Path=/; Expires=1765085004; passport_auth_status_ss=b8d801922a4b455b405bf6994fade073%2C063941b21aed31105bffa0d912bcf9fa; Domain=.tiktok.com; Path=/; Secure; Expires=1765085004; sid_guard=ade59ff71c0c0e5cc0fe1f23772b37c1%7C1762493004%7C15552000%7CWed%2C+06-May-2026+05%3A23%3A24+GMT; Domain=.tiktok.com; Path=/; Secure; Expires=1793597004; uid_tt=ac0557b89a0248004ba199e09ced5e656aa70515a78deb5b62cd048a83d31edc; Domain=.tiktok.com; Path=/; Secure; Expires=1778045004; uid_tt_ss=ac0557b89a0248004ba199e09ced5e656aa70515a78deb5b62cd048a83d31edc; Domain=.tiktok.com; Path=/; Secure; Expires=1778045004; sid_tt=ade59ff71c0c0e5cc0fe1f23772b37c1; Domain=.tiktok.com; Path=/; Secure; Expires=1778045004; sessionid=ade59ff71c0c0e5cc0fe1f23772b37c1; Domain=.tiktok.com; Path=/; Secure; Expires=1778045004; sessionid_ss=ade59ff71c0c0e5cc0fe1f23772b37c1; Domain=.tiktok.com; Path=/; Secure; Expires=1778045004; tt_session_tlb_tag=sttt%7C5%7CreWf9xwMDlzA_h8jdys3wf________-ji4fpfjT0V1140MZnLSHWNBnXgRLIZvw1fxmxRRmvw7s%3D; Domain=.tiktok.com; Path=/; Secure; Expires=1778045004; sid_ucp_v1=1.0.0-KDYzMTBmY2U1ODFjN2FkYjNmOGUwYWE1YjcwYTk2N2FkYzhhMjMxMTEKIQiSiNvUwN_XhmkQzIS2yAYYswsgDDC1vrXIBjgIQBJIBBADGgJteSIgYWRlNTlmZjcxYzBjMGU1Y2MwZmUxZjIzNzcyYjM3YzE; Domain=.tiktok.com; Path=/; Secure; Expires=1778045004; ssid_ucp_v1=1.0.0-KDYzMTBmY2U1ODFjN2FkYjNmOGUwYWE1YjcwYTk2N2FkYzhhMjMxMTEKIQiSiNvUwN_XhmkQzIS2yAYYswsgDDC1vrXIBjgIQBJIBBADGgJteSIgYWRlNTlmZjcxYzBjMGU1Y2MwZmUxZjIzNzcyYjM3YzE; Domain=.tiktok.com; Path=/; Secure; Expires=1778045004; store-country-code=vn; Domain=.tiktok.com; Path=/; Expires=1794029034; store-country-code-src=uid; Domain=.tiktok.com; Path=/; Expires=1794029034; tt-target-idc=alisg; Domain=.tiktok.com; Path=/; Expires=1794029034; tt-target-idc-sign=X46gRkvSgmGWHXja-gzeN1KwdE4cBtH3zFXAhG3-BtWzH-YdFZEQct_uBwMTYtfjrNxqy_GJyyU9vrDSU9xBVMhZYzNMj8Yj-vL3ZdUiBlJfwT_RyqsMw9cBp-UMAurlaLw7iKPn1sOB_2Mr4OgfdC72r1rSon8aLN6RpZxfHlcPgzQDAzxGLO1WCcDi3Grn071JYzpIP3H4Uj5tKf5cHSGRn8O-z3hwE-QaTWdxP_Dv9m7mqKXg9LpTBaiRQ0apSWQMga4QK4y5B4To6e0pZD8oaixa2PVdqGeLesDSGOjsT94m5Qtsw2dBLvi1Cl2PDtg34s_m8F2kwZanwVGyMx5JeHbhEA1jVyuFTZ4wmF-6mQMCj4IoVYUBqf6cEHJl1nz6p3h7j4AFPdhgbDj7nwn0zI1o0xP8WGmE_kn9e53ehBx6IU-iOQJ-JXc_4e8_1n_tP7nZqBQAfB5B-a8mW0iUyH2XBzKKIebPZ8u02eRKDVUUZnutFcgBXjbQW4hW; Domain=.tiktok.com; Path=/; Expires=1794029034; ttwid=1%7CyHVVoWeMmc-3HMQzGeLAWTKsoEmn5lOxHLhrceV4g3w%7C1762493033%7Caa33d6157603beb187ae2fd554015cf463e69a9385fbc54d7a3e7a848a9df8fc; Domain=.tiktok.com; Path=/; Secure; Expires=1794029034; store-idc=alisg; Domain=.tiktok.com; Path=/; Expires=1794029034; store-country-sign=MEIEDGNAqWqR2a0er4zjeAQgMuurAVNuf3SOpc_lCsUS6OVOTEMJPGY7fje3VCShvuYEEKSUWUChT9xgz3oinfsoj_8; Domain=.tiktok.com; Path=/; Expires=1794029034; odin_tt=fdb338ea9924b66e069cd3826b52e91602d6c7c70440ed4a45253d1bdcb67e7b33079c363923c1afe01be7d6a0aed5f094b6d26ad61219129e2c4adf8ef71b17c80e515b61a158847d9b8a0bdf5ce20d; Domain=.tiktok.com; Path=/; Expires=1794029677; msToken=\"kAcg9UuK5ZrneVDkYKsMPRcYLs1WAe9Bb0dpY3v2-xiyVx5Y6WfL8b6hWSn8iwVU3aEtG7I1jp1bvznmNsWneQmhuN9QHhnLK0KGHJ3hFP03j-bKzuS-NgPmvvyp3T7C_urkuuRQ27R5xw==\"; Domain=.tiktok.com; Path=/; Secure; Expires=1763396065",
    "format": "play - 1080x1920",
    "_type": "video",
    "_version": {
      "version": "2025.10.22",
      "release_git_head": "c9356f308dd3c5f9f494cb40ed14c5df017b4fe0",
      "repository": "yt-dlp/yt-dlp"
    }
  },
  "comments": [
    {
      "cid": "7292025308084404999",
      "text": "lên video gốc đi",
      "author": "One Hight",
      "create_time": 1697806955,
      "like_count": 0,
      "reply_count": 0,
      "replies": []
    },
    {
      "cid": "7298330435355493121",
      "text": "@FB: Trần Công Vinh 🧸🥀",
      "author": "💦💤💨",
      "create_time": 1699274986,
      "like_count": 0,
      "reply_count": 0,
      "replies": [
        {
          "aweme_id": "7255558002583981317",
          "cid": "7298330576284664577",
          "collect_stat": 0,
          "comment_language": "ms",
          "comment_post_item_ids": null,
          "create_time": 1699275023,
          "digg_count": 0,
          "forbid_reply_with_video": true,
          "image_list": null,
          "is_author_digged": false,
          "is_comment_translatable": true,
          "is_high_purchase_intent": false,
          "label_list": null,
          "no_show": false,
          "reply_comment": null,
          "reply_id": "7298330435355493121",
          "reply_to_reply_id": "7298330504411087618",
          "share_info": {
            "acl": {
              "code": 0,
              "extra": "{}"
            },
            "desc": "💦💤💨’s comment: dmm",
            "title": "Túi thần chửi =)#fyp #capcut #fypシ #fypシ゚viral #xuhuong #xuhuongtiktok #trending #trend #xuhuongtiktok2023 #xuhuong2023 #vba2023 #funnyvideos #funnyvideo #meme #foryou #funny ",
            "url": "https://m.tiktok.com/v/7255558002583981317.html?_d=f09gf88977dfid&comment_author_id=7037734691252077570&preview_pb=0&share_comment_id=7298330576284664577&share_item_id=7255558002583981317&sharer_language=en&source=h5_m&u_code=f09gf5a9194j7d"
          },
          "status": 1,
          "stick_position": 0,
          "text": "dmm",
          "text_extra": [],
          "trans_btn_style": 1,
          "user": {
            "account_labels": null,
            "ad_cover_url": null,
            "advance_feature_item_order": null,
            "advanced_feature_info": null,
            "avatar_thumb": {
              "uri": "tos-alisg-avt-0068/f649b902fd4d2476a1ce9cf3bc6446cc",
              "url_list": [
                "https://p16-sign-sg.tiktokcdn.com/tos-alisg-avt-0068/f649b902fd4d2476a1ce9cf3bc6446cc~tplv-tiktokx-cropcenter:100:100.jpg?dr=14579&refresh_token=6010a88f&x-expires=1762617600&x-signature=4f5V2z4yGLdbjqaP6ybLrzuP%2F3w%3D&t=4d5b0474&ps=13740610&shp=30310797&shcp=ff37627b&idc=my",
                "https://p16-sign-sg.tiktokcdn.com/tos-alisg-avt-0068/f649b902fd4d2476a1ce9cf3bc6446cc~tplv-tiktokx-cropcenter:100:100.jpeg?dr=14579&refresh_token=db76f318&x-expires=1762617600&x-signature=K6cq7%2BGjsOl6WpA4IGeuxqmJO3Q%3D&t=4d5b0474&ps=13740610&shp=30310797&shcp=ff37627b&idc=my"
              ],
              "url_prefix": null
            },
            "bold_fields": null,
            "can_message_follow_status_list": null,
            "can_set_geofencing": null,
            "cha_list": null,
            "cover_url": null,
            "custom_verify": "",
            "enterprise_verify_reason": "",
            "events": null,
            "followers_detail": null,
            "geofencing": null,
            "homepage_bottom_toast": null,
            "item_list": null,
            "mutual_relation_avatars": null,
            "need_points": null,
            "nickname": "💦💤💨",
            "platform_sync_info": null,
            "predicted_age_group": "-1",
            "relative_users": null,
            "search_highlight": null,
            "sec_uid": "MS4wLjABAAAAeCtD10IwgNNXtdyZ4Zpcv0iyRSOYI9xoFtJBqO-jcIvvaYqka-l7EIFrhS020nJh",
            "shield_edit_field_info": null,
            "type_label": null,
            "uid": "7037734691252077570",
            "unique_id": "buigiang2012",
            "user_profile_guide": null,
            "user_tags": null,
            "white_cover_url": null
          },
          "user_buried": false,
          "user_digged": 0
        }
      ]
    },
    {
      "cid": "7282966923599463176",
      "text": "@Duy:))",
      "author": "Minh tram tinh 🗣️🔥💥",
      "create_time": 1695702055,
      "like_count": 1,
      "reply_count": 0,
      "replies": []
    },
    {
      "cid": "7268543472892969733",
      "text": "@cuhp 🐸👀",
      "author": "thnglminh076",
      "create_time": 1692339668,
      "like_count": 1,
      "reply_count": 0,
      "replies": []
    },
    {
      "cid": "7267814738624217861",
      "text": "@nhiem1132010",
      "author": "K ?",
      "create_time": 1692169998,
      "like_count": 1,
      "reply_count": 0,
      "replies": []
    },
    {
      "cid": "7561043708389573396",
      "text": "🤡",
      "author": "Hoan Bùi",
      "create_time": 1760442680,
      "like_count": 0,
      "reply_count": 0,
      "replies": []
    },
    {
      "cid": "7305118139854766855",
      "text": "@Trần An2855",
      "author": "Định",
      "create_time": 1700855391,
      "like_count": 0,
      "reply_count": 0,
      "replies": []
    },
    {
      "cid": "7314327921747821313",
      "text": "@lộc chơi đá lớp 5E",
      "author": "️",
      "create_time": 1702999691,
      "like_count": 0,
      "reply_count": 0,
      "replies": []
    }
  ]
}